<?xml version="1.0" encoding="utf-8" ?>
<deck name="Olvia Walker">
 <main>
  <card id="11155" passcode="62098216">Evil★Twins Ki-sikil &amp; Lil-la</card>
  <card id="10561" passcode="71278040">Parallel eXceed</card>
  <card id="9942" passcode="21251800">Light Bringer Lucifer</card>
  <card id="9942" passcode="21251800">Light Bringer Lucifer</card>
  <card id="9942" passcode="21251800">Light Bringer Lucifer</card>
  <card id="14613" passcode="68075840">Power Pro Knight Sisters</card>
  <card id="14613" passcode="68075840">Power Pro Knight Sisters</card>
  <card id="14613" passcode="68075840">Power Pro Knight Sisters</card>
  <card id="8612" passcode="63528891">Backup Secretary</card>
  <card id="8612" passcode="63528891">Backup Secretary</card>
  <card id="11151" passcode="36326160">Live☆Twin Ki-sikil</card>
  <card id="11151" passcode="36326160">Live☆Twin Ki-sikil</card>
  <card id="11151" passcode="36326160">Live☆Twin Ki-sikil</card>
  <card id="11527" passcode="54257392">Live☆Twin Ki-sikil Frost</card>
  <card id="11527" passcode="54257392">Live☆Twin Ki-sikil Frost</card>
  <card id="11152" passcode="73810864">Live☆Twin Lil-la</card>
  <card id="11152" passcode="73810864">Live☆Twin Lil-la</card>
  <card id="11152" passcode="73810864">Live☆Twin Lil-la</card>
  <card id="16303" passcode="82699999">Live☆Twin Lil-la Sweet</card>
  <card id="16303" passcode="82699999">Live☆Twin Lil-la Sweet</card>
  <card id="11269" passcode="81078880">Live☆Twin Lil-la Treat</card>
  <card id="11269" passcode="81078880">Live☆Twin Lil-la Treat</card>
  <card id="11806" passcode="37582948">Live☆Twin Sunny&#39;s Snitch</card>
  <card id="11806" passcode="37582948">Live☆Twin Sunny&#39;s Snitch</card>
  <card id="11806" passcode="37582948">Live☆Twin Sunny&#39;s Snitch</card>
  <card id="11158" passcode="61976639">Secret Password</card>
  <card id="11158" passcode="61976639">Secret Password</card>
  <card id="11158" passcode="61976639">Secret Password</card>
  <card id="11156" passcode="08083925">Live☆Twin Home</card>
  <card id="11156" passcode="08083925">Live☆Twin Home</card>
  <card id="11160" passcode="34365442">Evil★Twin GG EZ</card>
  <card id="11159" passcode="98360333">Evil★Twin Challenge</card>
  <card id="11159" passcode="98360333">Evil★Twin Challenge</card>
  <card id="11161" passcode="60759087">Evil★Twin Present</card>
  <card id="11161" passcode="60759087">Evil★Twin Present</card>
  <card id="7207" passcode="0911883">Unexpected Dai</card>
  <card id="7207" passcode="0911883">Unexpected Dai</card>
  <card id="7207" passcode="0911883">Unexpected Dai</card>
  <card id="168" passcode="10667321">Ancient Rules</card>
  <card id="168" passcode="10667321">Ancient Rules</card>
 </main>
 <side>
 </side>
 <extra>
  <card id="5369789" passcode="">Dark Bringer Lucifer</card>
  <card id="11153" passcode="09205573">Evil★Twin Ki-sikil</card>
  <card id="11153" passcode="09205573">Evil★Twin Ki-sikil</card>
  <card id="11154" passcode="36609518">Evil★Twin Lil-la</card>
  <card id="11154" passcode="36609518">Evil★Twin Lil-la</card>
  <card id="16327" passcode="06636319">Evil★Twin Ki-sikil Deal</card>
  <card id="9171" passcode="38342335">Knightmare Unicorn</card>
  <card id="9170" passcode="02857636">Knightmare Phoenix</card>
  <card id="5369772" passcode="">Fairy Idol</card>
  <card id="5369772" passcode="">Fairy Idol</card>
 </extra>
</deck>